{
  "name": "GoalWonWhenInhabitants",
  "category": "misc_multiplayer_goals",
  "documentation": "Wins the multiplayer match when the given number of inhabitants is reached. Can be restricted to count soldiers only.\n\n*Note*: Shows text in top-right-corner automatically.",
  "parameters": [
    {
      "name": "NumberInhabitants",
      "type": "NUMBER"
    },
    {
      "name": "SoldiersOnly",
      "type": "NUMBER",
      "numberRange": {
        "min": 0,
        "max": 1
      },
      "numberHint": [
        "All",
        "Soldiers only"
      ]
    }
  ]
}
